openziti/__init__.py
openziti/__main__.py
openziti/_version.py
openziti/context.py
openziti/decor.py
openziti/zitilib.py
openziti/zitisock.py
openziti/lib/ziti.dll
openziti-0.6.0.dist-info/LICENSE
openziti-0.6.0.dist-info/METADATA
openziti-0.6.0.dist-info/WHEEL
openziti-0.6.0.dist-info/top_level.txt
openziti-0.6.0.dist-info/RECORD
