Metadata-Version: 2.1
Name: openziti
Version: 0.6.0
Summary: Ziti Python SDK
Home-page: https://github.com/openziti/ziti-sdk-py
Author: OpenZiti Developers
Author-email: developers@openziti.org
License: Apache 2.0
Project-URL: Documentation, https://openziti.github.io/ziti/overview.html
Project-URL: Source, https://github.com/openziti/ziti-sdk-py
Project-URL: Tracker, https://github.com/openziti/ziti-sdk-py/issues
Project-URL: Discussion, https://openziti.discourse.group/
Classifier: Development Status :: 3 - Alpha
Classifier: Intended Audience :: Developers
Classifier: License :: OSI Approved :: Apache Software License
Classifier: Operating System :: POSIX :: Linux
Classifier: Programming Language :: Python :: 3
Classifier: Programming Language :: Python :: 3.4
Classifier: Programming Language :: Python :: 3.5
License-File: LICENSE
